<?xml version="1.0" encoding="UTF-8"?>
<personnage name="COPS" version="1.0" gencrossVersion="1.14"
	xmlns:xsi="http://www.w3.org/2001/XMLSchema-instance"
	xsi:noNamespaceSchemaLocation="http://mrprez.dyndns.org:8080/gencross-web/gencross-plugin.xsd">
	<phase name="Caractéristiques" />
	<phaseList>
		<phase name="Caractéristiques" />
		<phase name="Compétences de bases" />
		<phase name="Compétences" />
		<phase name="Historique" />
	</phaseList>
	<pointPools>
		<pool name="Caractéristiques" remaining="14" total="14" toEmpty="true" />
		<pool name="Compétences" remaining="10" total="10" toEmpty="false" />
		<pool name="Stages" remaining="3" total="3" toEmpty="false" />
	</pointPools>
	<properties>
		<property editable="true" name="Nom">
			<Value class="com.mrprez.gencross.value.StringValue"></Value>
		</property>
		<property editable="true" name="Prénom">
			<Value class="com.mrprez.gencross.value.StringValue"></Value>
		</property>
		<property editable="true" name="Surnom">
			<Value class="com.mrprez.gencross.value.StringValue"></Value>
		</property>
		<property editable="true" name="Grade">
			<Value class="com.mrprez.gencross.value.IntValue">0</Value>
		</property>
		<property editable="false" name="Caracteristiques">
			<propertiesList fixe="true" open="false">
				<properties>
					<property editable="true" name="Carrure">
						<Value class="com.mrprez.gencross.value.IntValue">2</Value>
						<min>
							<Value class="com.mrprez.gencross.value.IntValue">2</Value>
						</min>
						<max>
							<Value class="com.mrprez.gencross.value.IntValue">5</Value>
						</max>
					</property>
					<property editable="true" name="Charme">
						<Value class="com.mrprez.gencross.value.IntValue">2</Value>
						<min>
							<Value class="com.mrprez.gencross.value.IntValue">2</Value>
						</min>
						<max>
							<Value class="com.mrprez.gencross.value.IntValue">5</Value>
						</max>
					</property>
					<property editable="true" name="Coordination">
						<Value class="com.mrprez.gencross.value.IntValue">2</Value>
						<min>
							<Value class="com.mrprez.gencross.value.IntValue">2</Value>
						</min>
						<max>
							<Value class="com.mrprez.gencross.value.IntValue">5</Value>
						</max>
					</property>
					<property editable="true" name="Education">
						<Value class="com.mrprez.gencross.value.IntValue">2</Value>
						<min>
							<Value class="com.mrprez.gencross.value.IntValue">2</Value>
						</min>
						<max>
							<Value class="com.mrprez.gencross.value.IntValue">5</Value>
						</max>
					</property>
					<property editable="true" name="Perception">
						<Value class="com.mrprez.gencross.value.IntValue">2</Value>
						<min>
							<Value class="com.mrprez.gencross.value.IntValue">2</Value>
						</min>
						<max>
							<Value class="com.mrprez.gencross.value.IntValue">5</Value>
						</max>
					</property>
					<property editable="true" name="Réflexe">
						<Value class="com.mrprez.gencross.value.IntValue">2</Value>
						<min>
							<Value class="com.mrprez.gencross.value.IntValue">2</Value>
						</min>
						<max>
							<Value class="com.mrprez.gencross.value.IntValue">5</Value>
						</max>
					</property>
					<property editable="false" name="Init. min">
						<Value class="com.mrprez.gencross.value.IntValue">1</Value>
					</property>
					<property editable="true" name="Sang froid">
						<Value class="com.mrprez.gencross.value.IntValue">2</Value>
						<min>
							<Value class="com.mrprez.gencross.value.IntValue">2</Value>
						</min>
						<max>
							<Value class="com.mrprez.gencross.value.IntValue">5</Value>
						</max>
					</property>
				</properties>
			</propertiesList>
			<historyFactory
				class="com.mrprez.gencross.history.ProportionalHistoryFactory">
				<pointPool>Caractéristiques</pointPool>
				<args></args>
			</historyFactory>
		</property>
		<property editable="false" name="Points de vie">
			<Value class="com.mrprez.gencross.value.IntValue">26</Value>
		</property>
		<property editable="false" name="Point d'adrénaline">
			<Value class="com.mrprez.gencross.value.IntValue">0</Value>
		</property>
		<property editable="false" name="Point d'ancienneté">
			<Value class="com.mrprez.gencross.value.IntValue">0</Value>
		</property>
		<property editable="false" name="Compétences">
			<propertiesList fixe="true" open="false">
				<properties>
					<property name="Arme d’Épaule" editable="false">
						<Value class="com.mrprez.gencross.value.IntValue">8</Value>
						<min>
							<Value class="com.mrprez.gencross.value.IntValue">6</Value>
						</min>
						<max>
							<Value class="com.mrprez.gencross.value.IntValue">8</Value>
						</max>
						<propertiesList fixe="true" open="true">
							<properties></properties>
							<defaultProperty>
								<property editable="true" name="">
									<Value class="com.mrprez.gencross.value.IntValue">6</Value>
									<min><Value class="com.mrprez.gencross.value.IntValue">6</Value></min>
									<max><Value class="com.mrprez.gencross.value.IntValue">6</Value></max>
								</property>
							</defaultProperty>
						</propertiesList>
					</property>
					<property name="Arme de Contact" editable="false">
						<Value class="com.mrprez.gencross.value.IntValue">8</Value>
						<min>
							<Value class="com.mrprez.gencross.value.IntValue">7</Value>
						</min>
						<max>
							<Value class="com.mrprez.gencross.value.IntValue">8</Value>
						</max>
						<propertiesList fixe="true" open="true">
							<properties></properties>
							<defaultProperty>
								<property editable="true" name="">
									<Value class="com.mrprez.gencross.value.IntValue">7</Value>
									<min><Value class="com.mrprez.gencross.value.IntValue">6</Value></min>
									<max><Value class="com.mrprez.gencross.value.IntValue">7</Value></max>
								</property>
							</defaultProperty>
						</propertiesList>
					</property>
					<property name="Arme de Poing" editable="false">
						<Value class="com.mrprez.gencross.value.IntValue">7</Value>
						<min>
							<Value class="com.mrprez.gencross.value.IntValue">5</Value>
						</min>
						<max>
							<Value class="com.mrprez.gencross.value.IntValue">7</Value>
						</max>
					</property>
					<property name="Arme Lourde" editable="false">
						<propertiesList fixe="true" open="true">
							<properties></properties>
							<defaultProperty>
								<property editable="true" name="">
									<Value class="com.mrprez.gencross.value.IntValue">10</Value>
									<min><Value class="com.mrprez.gencross.value.IntValue">8</Value></min>
									<max><Value class="com.mrprez.gencross.value.IntValue">10</Value></max>
								</property>
							</defaultProperty>
						</propertiesList>
					</property>
					<property name="Athlétisme" editable="false">
						<Value class="com.mrprez.gencross.value.IntValue">10</Value>
						<min>
							<Value class="com.mrprez.gencross.value.IntValue">8</Value>
						</min>
						<max>
							<Value class="com.mrprez.gencross.value.IntValue">10</Value>
						</max>
					</property>
					<property name="Bureaucratie" editable="false">
						<Value class="com.mrprez.gencross.value.IntValue">8</Value>
						<min>
							<Value class="com.mrprez.gencross.value.IntValue">6</Value>
						</min>
						<max>
							<Value class="com.mrprez.gencross.value.IntValue">8</Value>
						</max>
					</property>
					<property name="Conduite" editable="false">
						<Value class="com.mrprez.gencross.value.IntValue">9</Value>
						<propertiesList fixe="true" open="true">
							<properties>
								<property name="Voiture" editable="false">
									<Value class="com.mrprez.gencross.value.IntValue">7</Value>
									<min>
										<Value class="com.mrprez.gencross.value.IntValue">5</Value>
									</min>
									<max>
										<Value class="com.mrprez.gencross.value.IntValue">7</Value>
									</max>
								</property>
							</properties>
							<defaultProperty>
								<property name="" editable="true">
									<Value class="com.mrprez.gencross.value.IntValue">9</Value>
									<min>
										<Value class="com.mrprez.gencross.value.IntValue">7</Value>
									</min>
									<max>
										<Value class="com.mrprez.gencross.value.IntValue">9</Value>
									</max>
								</property>
							</defaultProperty>
						</propertiesList>
					</property>
					<property name="Connaissance" editable="false">
						<propertiesList fixe="true" open="true">
							<properties></properties>
							<defaultProperty>
								<property name="" editable="true">
									<Value class="com.mrprez.gencross.value.IntValue">10</Value>
									<min>
										<Value class="com.mrprez.gencross.value.IntValue">8</Value>
									</min>
									<max>
										<Value class="com.mrprez.gencross.value.IntValue">10</Value>
									</max>
								</property>
							</defaultProperty>
						</propertiesList>
					</property>
					<property name="Corps à Corps" editable="false">
						<Value class="com.mrprez.gencross.value.IntValue">8</Value>
						<propertiesList fixe="false" open="true">
							<properties></properties>
							<propertyChoice>
								<property name="coups" editable="true">
									<Value class="com.mrprez.gencross.value.IntValue">8</Value>
									<min>
										<Value class="com.mrprez.gencross.value.IntValue">7</Value>
									</min>
									<max>
										<Value class="com.mrprez.gencross.value.IntValue">8</Value>
									</max>
								</property>
								<property name="projections" editable="true">
									<Value class="com.mrprez.gencross.value.IntValue">8</Value>
									<min>
										<Value class="com.mrprez.gencross.value.IntValue">7</Value>
									</min>
									<max>
										<Value class="com.mrprez.gencross.value.IntValue">8</Value>
									</max>
								</property>
								<property name="immobilisations" editable="true">
									<Value class="com.mrprez.gencross.value.IntValue">8</Value>
									<min>
										<Value class="com.mrprez.gencross.value.IntValue">7</Value>
									</min>
									<max>
										<Value class="com.mrprez.gencross.value.IntValue">8</Value>
									</max>
								</property>
							</propertyChoice>
							<defaultProperty>
								<property name="" editable="true">
									<Value class="com.mrprez.gencross.value.IntValue">8</Value>
									<min>
										<Value class="com.mrprez.gencross.value.IntValue">6</Value>
									</min>
									<max>
										<Value class="com.mrprez.gencross.value.IntValue">8</Value>
									</max>
								</property>
							</defaultProperty>
						</propertiesList>
					</property>
					<property name="Déguisement" editable="false">
						<Value class="com.mrprez.gencross.value.IntValue">10</Value>
						<min>
							<Value class="com.mrprez.gencross.value.IntValue">8</Value>
						</min>
						<max>
							<Value class="com.mrprez.gencross.value.IntValue">10</Value>
						</max>
					</property>
					<property name="Discrétion" editable="false">
						<Value class="com.mrprez.gencross.value.IntValue">7</Value>
						<min>
							<Value class="com.mrprez.gencross.value.IntValue">5</Value>
						</min>
						<max>
							<Value class="com.mrprez.gencross.value.IntValue">7</Value>
						</max>
					</property>
					<property name="Électronique" editable="false">
						<Value class="com.mrprez.gencross.value.IntValue">10</Value>
						<min>
							<Value class="com.mrprez.gencross.value.IntValue">8</Value>
						</min>
						<max>
							<Value class="com.mrprez.gencross.value.IntValue">10</Value>
						</max>
					</property>
					<property name="Éloquence" editable="false">
						<Value class="com.mrprez.gencross.value.IntValue">10</Value>
						<min>
							<Value class="com.mrprez.gencross.value.IntValue">7</Value>
						</min>
						<max>
							<Value class="com.mrprez.gencross.value.IntValue">10</Value>
						</max>
					</property>
					<property name="Falsification" editable="false">
						<Value class="com.mrprez.gencross.value.IntValue">10</Value>
						<min>
							<Value class="com.mrprez.gencross.value.IntValue">8</Value>
						</min>
						<max>
							<Value class="com.mrprez.gencross.value.IntValue">10</Value>
						</max>
					</property>
					<property name="Informatique" editable="false">
						<Value class="com.mrprez.gencross.value.IntValue">7</Value>
						<min>
							<Value class="com.mrprez.gencross.value.IntValue">6</Value>
						</min>
						<max>
							<Value class="com.mrprez.gencross.value.IntValue">7</Value>
						</max>
						<propertiesList fixe="true" open="true">
							<properties></properties>
							<defaultProperty>
								<property editable="true" name="">
									<Value class="com.mrprez.gencross.value.IntValue">6</Value>
									<min><Value class="com.mrprez.gencross.value.IntValue">5</Value></min>
									<max><Value class="com.mrprez.gencross.value.IntValue">6</Value></max>
								</property>
							</defaultProperty>
						</propertiesList>
					</property>
					<property name="Instinct de Flic" editable="false">
						<Value class="com.mrprez.gencross.value.IntValue">9</Value>
						<min>
							<Value class="com.mrprez.gencross.value.IntValue">7</Value>
						</min>
						<max>
							<Value class="com.mrprez.gencross.value.IntValue">9</Value>
						</max>
					</property>
					<property name="Intimidation" editable="false">
						<Value class="com.mrprez.gencross.value.IntValue">10</Value>
						<min>
							<Value class="com.mrprez.gencross.value.IntValue">7</Value>
						</min>
						<max>
							<Value class="com.mrprez.gencross.value.IntValue">10</Value>
						</max>
					</property>
					<property name="Jeu" editable="false">
						<Value class="com.mrprez.gencross.value.IntValue">10</Value>
						<min>
							<Value class="com.mrprez.gencross.value.IntValue">8</Value>
						</min>
						<max>
							<Value class="com.mrprez.gencross.value.IntValue">10</Value>
						</max>
					</property>
					<property name="Lancer" editable="false">
						<Value class="com.mrprez.gencross.value.IntValue">10</Value>
						<min>
							<Value class="com.mrprez.gencross.value.IntValue">8</Value>
						</min>
						<max>
							<Value class="com.mrprez.gencross.value.IntValue">10</Value>
						</max>
					</property>
					<property name="Mécanique" editable="false">
						<Value class="com.mrprez.gencross.value.IntValue">10</Value>
						<min>
							<Value class="com.mrprez.gencross.value.IntValue">8</Value>
						</min>
						<max>
							<Value class="com.mrprez.gencross.value.IntValue">10</Value>
						</max>
					</property>
					<property name="Médecine" editable="false">
						<Value class="com.mrprez.gencross.value.IntValue">10</Value>
						<min>
							<Value class="com.mrprez.gencross.value.IntValue">8</Value>
						</min>
						<max>
							<Value class="com.mrprez.gencross.value.IntValue">10</Value>
						</max>
						<propertiesList fixe="true" open="true">
							<properties></properties>
							<defaultProperty>
								<property editable="true" name="">
									<Value class="com.mrprez.gencross.value.IntValue">7</Value>
									<min><Value class="com.mrprez.gencross.value.IntValue">2</Value></min>
									<max><Value class="com.mrprez.gencross.value.IntValue">7</Value></max>
								</property>
							</defaultProperty>
						</propertiesList>
					</property>
					<property name="Pilotage" editable="false">
						<propertiesList fixe="true" open="true">
							<properties></properties>
							<defaultProperty>
								<property editable="true" name="">
									<Value class="com.mrprez.gencross.value.IntValue">10</Value>
									<min><Value class="com.mrprez.gencross.value.IntValue">8</Value></min>
									<max><Value class="com.mrprez.gencross.value.IntValue">10</Value></max>
								</property>
							</defaultProperty>
						</propertiesList>
					</property>
					<property name="Premiers Secours" editable="false">
						<Value class="com.mrprez.gencross.value.IntValue">10</Value>
						<min>
							<Value class="com.mrprez.gencross.value.IntValue">8</Value>
						</min>
						<max>
							<Value class="com.mrprez.gencross.value.IntValue">10</Value>
						</max>
					</property>
					<property name="Psychologie" editable="false">
						<Value class="com.mrprez.gencross.value.IntValue">10</Value>
						<min>
							<Value class="com.mrprez.gencross.value.IntValue">8</Value>
						</min>
						<max>
							<Value class="com.mrprez.gencross.value.IntValue">10</Value>
						</max>
					</property>
					<property name="Rhétorique" editable="false">
						<Value class="com.mrprez.gencross.value.IntValue">10</Value>
						<min>
							<Value class="com.mrprez.gencross.value.IntValue">7</Value>
						</min>
						<max>
							<Value class="com.mrprez.gencross.value.IntValue">10</Value>
						</max>
					</property>
					<property name="Scène de Crime" editable="false">
						<Value class="com.mrprez.gencross.value.IntValue">10</Value>
						<min>
							<Value class="com.mrprez.gencross.value.IntValue">8</Value>
						</min>
						<max>
							<Value class="com.mrprez.gencross.value.IntValue">10</Value>
						</max>
					</property>
					<property name="Tir en Rafale" editable="false">
						<Value class="com.mrprez.gencross.value.IntValue">10</Value>
						<min>
							<Value class="com.mrprez.gencross.value.IntValue">8</Value>
						</min>
						<max>
							<Value class="com.mrprez.gencross.value.IntValue">10</Value>
						</max>
						<propertiesList fixe="true" open="true">
							<properties></properties>
							<defaultProperty>
								<property editable="true" name="">
									<Value class="com.mrprez.gencross.value.IntValue">8</Value>
									<min><Value class="com.mrprez.gencross.value.IntValue">8</Value></min>
									<max><Value class="com.mrprez.gencross.value.IntValue">8</Value></max>
								</property>
							</defaultProperty>
						</propertiesList>
					</property>
				</properties>
			</propertiesList>
		</property>

	</properties>
	<beforeChangeValueListeners>
	</beforeChangeValueListeners>
	<afterChangeValueListeners>
		<listener class="com.mrprez.gencross.listener.custom.CustomAfterChangeValueListener">
			<pattern>Compétences#[^#]*</pattern>
			<arg name="method">changeCompetences</arg>
		</listener>
	</afterChangeValueListeners>
	<beforeAddPropertyListeners>
	</beforeAddPropertyListeners>
	<afterAddPropertyListeners>
	</afterAddPropertyListeners>
	<beforeDeletePropertyListeners>
	</beforeDeletePropertyListeners>
	<afterDeletePropertyListeners>
	</afterDeletePropertyListeners>
	<passToNextPhaseListeners>
		<listener class="com.mrprez.gencross.listener.impl.EditableListener">
			<phase>Caractéristiques</phase>
			<arg name="propertyName">Compétences#Éloquence</arg>
			<arg name="editable">true</arg>
		</listener>
		<listener class="com.mrprez.gencross.listener.impl.EditableListener">
			<phase>Caractéristiques</phase>
			<arg name="propertyName">Compétences#Intimidation</arg>
			<arg name="editable">true</arg>
		</listener>
		<listener class="com.mrprez.gencross.listener.impl.EditableListener">
			<phase>Caractéristiques</phase>
			<arg name="propertyName">Compétences#Rhétorique</arg>
			<arg name="editable">true</arg>
		</listener>
		<listener class="com.mrprez.gencross.listener.impl.EditableListener">
			<phase>Caractéristiques</phase>
			<arg name="pattern">Compétences#Corps à corps.*</arg>
			<arg name="editable">true</arg>
		</listener>
		<listener class="com.mrprez.gencross.listener.impl.ToEmptyListener">
			<phase>Compétences de bases</phase>
			<arg name="pointPool">Compétences</arg>
			<arg name="toEmpty">true</arg>
		</listener>
		<listener class="com.mrprez.gencross.impl.cops.SetMaxListener">
			<phase>Compétences de bases</phase>
			<arg name="pattern">Compétences#.*</arg>
		</listener>
		<listener class="com.mrprez.gencross.listener.custom.CustomPassToNextPhaseListener">
			<phase>Compétences de bases</phase>
			<arg name="method">goToPhaseCompetence</arg>
		</listener>
		
	</passToNextPhaseListeners>
	<formulas>
		<formula>Points de vie=#Caracteristiques#Carrure# * 3 + 20</formula>
		<formula>Caracteristiques#Init. min=3 - #Caracteristiques#Réflexe#</formula>
	</formulas>
	<history></history>
</personnage>
